<?xml version="1.0" encoding="UTF-8"?>
<!DOCTYPE hibernate-mapping PUBLIC "-//Hibernate/Hibernate Mapping DTD 3.0//EN" "http://hibernate.sourceforge.net/hibernate-mapping-3.0.dtd">
<hibernate-mapping package="com.mycompany.nncloudrestservice.model">
  <class name="Neuron" table="neurons">
      <id name="id" type="int">
          <column name="id_neuron" not-null="true"/>
          <generator class="native"/>
      </id>
      <list name="synapses_out" cascade="all" table="synapses">
          <key>
              <column name="id_neuron_out"/>
          </key>
          <one-to-many class="Synapse"/>
      </list>
      <list name="synapses_in" cascade="all" table="synapses">
          <key>
              <column name="id_neuron_in"/>
          </key>
          <one-to-many class="Synapse"/>
      </list>
      <list name="activation_functions" table="activation_functions" cascade="all">
          <key>
              <column name="id_activation_function" not-null="true"/>
          </key>
          <one-to-many class="ActivationFunction"/>
      </list>
  </class>
</hibernate-mapping>
